ez_ados/__init__.py
ez_ados/client.py
ez_ados/credentials.py
ez_ados/logs.py
ez_ados/models.py
ez_ados/version.py
ez_ados/base/__init__.py
ez_ados/base/clients.py
ez_ados/base/enums.py
ez_ados/base/models.py
ez_ados/base/validators.py
ez_ados/builds/__init__.py
ez_ados/builds/clients.py
ez_ados/builds/models.py
ez_ados/core/__init__.py
ez_ados/core/clients.py
ez_ados/core/models.py
ez_ados/git/__init__.py
ez_ados/git/clients.py
ez_ados/git/enums.py
ez_ados/git/models.py
ez_ados/git/pullrequests/__init__.py
ez_ados/git/pullrequests/clients.py
ez_ados/git/pullrequests/enums.py
ez_ados/git/pullrequests/models.py
ez_ados/pipelines/__init__.py
ez_ados/pipelines/clients.py
ez_ados/pipelines/enums.py
ez_ados/pipelines/models.py
ez_ados/policy/__init__.py
ez_ados/policy/configurations/__init__.py
ez_ados/policy/configurations/clients.py
ez_ados/policy/configurations/models.py
ez_ados/policy/types/__init__.py
ez_ados/policy/types/clients.py
ez_ados/policy/types/models.py
ez_ados/servicehooks/__init__.py
ez_ados/servicehooks/subscriptions/__init__.py
ez_ados/servicehooks/subscriptions/clients.py
ez_ados/servicehooks/subscriptions/enums.py
ez_ados/servicehooks/subscriptions/models.py
ez_ados-0.4.0.dist-info/METADATA
ez_ados-0.4.0.dist-info/WHEEL
ez_ados-0.4.0.dist-info/licenses/LICENSE
ez_ados-0.4.0.dist-info/RECORD
