Metadata-Version: 2.4
Name: ez_ados
Version: 0.4.0
Summary: A simple Python interface to interact with Azure DevOps API
Project-URL: Homepage, https://github.com/bigbrozer/ez-azure-devops
Author-email: Vincent BESANCON <contact@stash.vinzworld.fr>
License:                     GNU AFFERO GENERAL PUBLIC LICENSE
License-File: LICENSE
Keywords: 
Classifier: Development Status :: 4 - Beta
Classifier: License :: OSI Approved :: GNU Affero General Public License v3 or later (AGPLv3+)
Classifier: Programming Language :: Python :: 3
Requires-Python: >=3.12
Requires-Dist: azure-identity<2.0.0,>=1.25.0
Requires-Dist: httpx>=0.28.1
Requires-Dist: pydantic<3.0.0,>=2.11.10
